[{"__symbolic":"module","version":4,"metadata":{"VirtualScrollComponent":{"__symbolic":"class","decorators":[{"__symbolic":"call","expression":{"__symbolic":"reference","module":"@angular/core","name":"Component","line":3,"character":1},"arguments":[{"selector":"eui-virtual-scroll","template":"\n\t\t<div #body class=\"scroll-body f-full\">\n\t\t\t<div #top class=\"scroll-top\">\n\t\t\t\t<div *ngFor=\"let h of topHeights\" [style.height.px]=\"h\"></div>\n\t\t\t</div>\n\t\t\t<div #content class=\"scroll-content\">\n\t\t\t\t<ng-content></ng-content>\n\t\t\t</div>\n\t\t\t<div #bottom class=\"scroll-bottom\">\n\t\t\t\t<div *ngFor=\"let h of bottomHeights\" [style.height.px]=\"h\"></div>\n\t\t\t</div>\n\t\t</div>\n\t","host":{"class":"f-column","$quoted$":["class"]}}]}],"members":{"bodyRef":[{"__symbolic":"property","decorators":[{"__symbolic":"call","expression":{"__symbolic":"reference","module":"@angular/core","name":"ViewChild","line":23,"character":2},"arguments":["body"]}]}],"topRef":[{"__symbolic":"property","decorators":[{"__symbolic":"call","expression":{"__symbolic":"reference","module":"@angular/core","name":"ViewChild","line":24,"character":2},"arguments":["top"]}]}],"bottomRef":[{"__symbolic":"property","decorators":[{"__symbolic":"call","expression":{"__symbolic":"reference","module":"@angular/core","name":"ViewChild","line":25,"character":2},"arguments":["bottom"]}]}],"contentRef":[{"__symbolic":"property","decorators":[{"__symbolic":"call","expression":{"__symbolic":"reference","module":"@angular/core","name":"ViewChild","line":26,"character":2},"arguments":["content"]}]}],"width":[{"__symbolic":"property","decorators":[{"__symbolic":"call","expression":{"__symbolic":"reference","module":"@angular/core","name":"Input","line":28,"character":2}}]}],"minWidth":[{"__symbolic":"property","decorators":[{"__symbolic":"call","expression":{"__symbolic":"reference","module":"@angular/core","name":"Input","line":29,"character":2}}]}],"maxWidth":[{"__symbolic":"property","decorators":[{"__symbolic":"call","expression":{"__symbolic":"reference","module":"@angular/core","name":"Input","line":30,"character":2}}]}],"height":[{"__symbolic":"property","decorators":[{"__symbolic":"call","expression":{"__symbolic":"reference","module":"@angular/core","name":"Input","line":31,"character":2}}]}],"minHeight":[{"__symbolic":"property","decorators":[{"__symbolic":"call","expression":{"__symbolic":"reference","module":"@angular/core","name":"Input","line":32,"character":2}}]}],"maxHeight":[{"__symbolic":"property","decorators":[{"__symbolic":"call","expression":{"__symbolic":"reference","module":"@angular/core","name":"Input","line":33,"character":2}}]}],"lazy":[{"__symbolic":"property","decorators":[{"__symbolic":"call","expression":{"__symbolic":"reference","module":"@angular/core","name":"Input","line":35,"character":2}}]}],"rowHeight":[{"__symbolic":"property","decorators":[{"__symbolic":"call","expression":{"__symbolic":"reference","module":"@angular/core","name":"Input","line":36,"character":2}}]}],"maxDivHeight":[{"__symbolic":"property","decorators":[{"__symbolic":"call","expression":{"__symbolic":"reference","module":"@angular/core","name":"Input","line":37,"character":2}}]}],"maxVisibleHeight":[{"__symbolic":"property","decorators":[{"__symbolic":"call","expression":{"__symbolic":"reference","module":"@angular/core","name":"Input","line":38,"character":2}}]}],"pageNumber":[{"__symbolic":"property","decorators":[{"__symbolic":"call","expression":{"__symbolic":"reference","module":"@angular/core","name":"Input","line":39,"character":2}}]}],"pageSize":[{"__symbolic":"property","decorators":[{"__symbolic":"call","expression":{"__symbolic":"reference","module":"@angular/core","name":"Input","line":40,"character":2}}]}],"total":[{"__symbolic":"property","decorators":[{"__symbolic":"call","expression":{"__symbolic":"reference","module":"@angular/core","name":"Input","line":41,"character":2}}]}],"onUpdate":[{"__symbolic":"property","decorators":[{"__symbolic":"call","expression":{"__symbolic":"reference","module":"@angular/core","name":"Output","line":43,"character":2},"arguments":["update"]}]}],"onPageChange":[{"__symbolic":"property","decorators":[{"__symbolic":"call","expression":{"__symbolic":"reference","module":"@angular/core","name":"Output","line":44,"character":2},"arguments":["pageChange"]}]}],"bodyScroll":[{"__symbolic":"property","decorators":[{"__symbolic":"call","expression":{"__symbolic":"reference","module":"@angular/core","name":"Output","line":45,"character":2}}]}],"data":[{"__symbolic":"property","decorators":[{"__symbolic":"call","expression":{"__symbolic":"reference","module":"@angular/core","name":"Input","line":48,"character":2}}]}],"__ctor__":[{"__symbolic":"constructor","parameters":[{"__symbolic":"reference","module":"@angular/core","name":"ChangeDetectorRef","line":104,"character":27},{"__symbolic":"reference","module":"@angular/core","name":"Renderer2","line":104,"character":61}]}],"ngAfterViewInit":[{"__symbolic":"method"}],"scrolling":[{"__symbolic":"method"}],"populate":[{"__symbolic":"method"}],"splitHeights":[{"__symbolic":"method"}],"loadPage":[{"__symbolic":"method"}],"fetchPage":[{"__symbolic":"method"}],"gotoPage":[{"__symbolic":"method"}],"refresh":[{"__symbolic":"method"}]}}}}]